{
    "USD": 1,
    "AED": 3.6725,
    "AFN": 69.0681,
    "ALL": 83.7374,
    "AMD": 383.925,
    "ANG": 1.79,
    "AOA": 921.9393,
    "ARS": 1286.0,
    "AUD": 1.5324,
    "AWG": 1.79,
    "AZN": 1.6985,
    "BAM": 1.6754,
    "BBD": 2.0,
    "BDT": 121.5322,
    "BGN": 1.6755,
    "BHD": 0.376,
    "BIF": 2970.1451,
    "BMD": 1.0,
    "BND": 1.2824,
    "BOB": 6.9101,
    "BRL": 5.5821,
    "BSD": 1.0,
    "BTN": 86.2865,
    "BWP": 14.0162,
    "BYN": 3.1294,
    "BZD": 2.0,
    "CAD": 1.3701,
    "CDF": 2886.7438,
    "CHF": 0.7994,
    "CLP": 962.9273,
    "CNY": 7.1846,
    "COP": 4016.1852,
    "CRC": 504.1433,
    "CUP": 24.0,
    "CVE": 94.4552,
    "CZK": 21.1296,
    "DJF": 177.721,
    "DKK": 6.3879,
    "DOP": 60.3965,
    "DZD": 130.0292,
    "EGP": 49.241,
    "ERN": 15.0,
    "ETB": 136.6154,
    "EUR": 0.8566,
    "FJD": 2.253,
    "FKP": 0.7424,
    "FOK": 6.3882,
    "GBP": 0.7424,
    "GEL": 2.7106,
    "GGP": 0.7424,
    "GHS": 10.8711,
    "GIP": 0.7424,
    "GMD": 72.776,
    "GNF": 8697.9792,
    "GTQ": 7.6689,
    "GYD": 209.1756,
    "HKD": 7.8501,
    "HNL": 26.1451,
    "HRK": 6.4542,
    "HTG": 131.1997,
    "HUF": 342.3322,
    "IDR": 16315.9328,
    "ILS": 3.349,
    "IMP": 0.7424,
    "INR": 86.2881,
    "IQD": 1310.6673,
    "IRR": 42444.9156,
    "ISK": 122.2107,
    "JEP": 0.7424,
    "JMD": 160.083,
    "JOD": 0.709,
    "JPY": 147.6338,
    "KES": 129.0339,
    "KGS": 87.3514,
    "KHR": 4017.9577,
    "KID": 1.5325,
    "KMF": 421.4294,
    "KRW": 1383.6569,
    "KWD": 0.3053,
    "KYD": 0.8333,
    "KZT": 529.9475,
    "LAK": 21643.604,
    "LBP": 89500.0,
    "LKR": 301.3239,
    "LRD": 200.2886,
    "LSL": 17.6755,
    "LYD": 5.4192,
    "MAD": 9.0281,
    "MDL": 16.9811,
    "MGA": 4428.5248,
    "MKD": 52.933,
    "MMK": 2098.5177,
    "MNT": 3554.6658,
    "MOP": 8.0858,
    "MRU": 39.9559,
    "MUR": 45.5884,
    "MVR": 15.4139,
    "MWK": 1743.9425,
    "MXN": 18.6931,
    "MYR": 4.2354,
    "MZN": 63.6654,
    "NAD": 17.6755,
    "NGN": 1528.7297,
    "NIO": 36.7687,
    "NOK": 10.1717,
    "NPR": 138.0583,
    "NZD": 1.6751,
    "OMR": 0.3845,
    "PAB": 1.0,
    "PEN": 3.5612,
    "PGK": 4.1461,
    "PHP": 57.1089,
    "PKR": 285.1611,
    "PLN": 3.6384,
    "PYG": 7699.5143,
    "QAR": 3.64,
    "RON": 4.3458,
    "RSD": 100.5526,
    "RUB": 78.2333,
    "RWF": 1449.3159,
    "SAR": 3.75,
    "SBD": 8.2592,
    "SCR": 14.496,
    "SDG": 454.1776,
    "SEK": 9.5928,
    "SGD": 1.2824,
    "SHP": 0.7424,
    "SLE": 22.5871,
    "SLL": 22587.122,
    "SOS": 571.8812,
    "SRD": 36.7032,
    "SSP": 4691.5567,
    "STN": 20.9872,
    "SYP": 12885.7871,
    "SZL": 17.6755,
    "THB": 32.2856,
    "TJS": 9.6105,
    "TMT": 3.4999,
    "TND": 2.8771,
    "TOP": 2.3825,
    "TRY": 40.4545,
    "TTD": 6.7623,
    "TVD": 1.5325,
    "TWD": 29.3385,
    "TZS": 2602.265,
    "UAH": 41.8117,
    "UGX": 3566.8538,
    "UYU": 40.3225,
    "UZS": 12631.9812,
    "VES": 119.6662,
    "VND": 26064.0087,
    "VUV": 119.1105,
    "WST": 2.6668,
    "XAF": 561.9059,
    "XCD": 2.7,
    "XCG": 1.79,
    "XDR": 0.7325,
    "XOF": 561.9059,
    "XPF": 102.2222,
    "YER": 240.7453,
    "ZAR": 17.6656,
    "ZMW": 23.1377,
    "ZWL": 26.8064
}