{
    "USD": 1,
    "AED": 3.6725,
    "AFN": 66.6102,
    "ALL": 91.1901,
    "AMD": 387.077,
    "ANG": 1.79,
    "AOA": 915.5557,
    "ARS": 988.83,
    "AUD": 1.5175,
    "AWG": 1.79,
    "AZN": 1.7001,
    "BAM": 1.8083,
    "BBD": 2.0,
    "BDT": 119.528,
    "BGN": 1.8083,
    "BHD": 0.376,
    "BIF": 2911.6303,
    "BMD": 1.0,
    "BND": 1.3224,
    "BOB": 6.9232,
    "BRL": 5.7069,
    "BSD": 1.0,
    "BTN": 84.1048,
    "BWP": 13.3877,
    "BYN": 3.2853,
    "BZD": 2.0,
    "CAD": 1.3891,
    "CDF": 2838.9965,
    "CHF": 0.8655,
    "CLP": 948.7342,
    "CNY": 7.1358,
    "COP": 4320.5196,
    "CRC": 514.1759,
    "CUP": 24.0,
    "CVE": 101.9495,
    "CZK": 23.4443,
    "DJF": 177.721,
    "DKK": 6.8975,
    "DOP": 60.2638,
    "DZD": 133.3644,
    "EGP": 48.6935,
    "ERN": 15.0,
    "ETB": 118.5153,
    "EUR": 0.9246,
    "FJD": 2.2526,
    "FKP": 0.7707,
    "FOK": 6.8976,
    "GBP": 0.7707,
    "GEL": 2.729,
    "GGP": 0.7707,
    "GHS": 16.4903,
    "GIP": 0.7707,
    "GMD": 70.9548,
    "GNF": 8681.6324,
    "GTQ": 7.7335,
    "GYD": 209.0798,
    "HKD": 7.7714,
    "HNL": 25.2192,
    "HRK": 6.9663,
    "HTG": 131.7393,
    "HUF": 373.9091,
    "IDR": 15745.4535,
    "ILS": 3.7282,
    "IMP": 0.7707,
    "INR": 84.0988,
    "IQD": 1309.8819,
    "IRR": 42035.5627,
    "ISK": 137.7893,
    "JEP": 0.7707,
    "JMD": 158.3197,
    "JOD": 0.709,
    "JPY": 153.1299,
    "KES": 128.8353,
    "KGS": 85.4716,
    "KHR": 4086.0117,
    "KID": 1.5174,
    "KMF": 454.8667,
    "KRW": 1383.1724,
    "KWD": 0.3066,
    "KYD": 0.8333,
    "KZT": 490.204,
    "LAK": 21923.4013,
    "LBP": 89500.0,
    "LKR": 293.3915,
    "LRD": 191.9783,
    "LSL": 17.6999,
    "LYD": 4.8166,
    "MAD": 9.8595,
    "MDL": 17.9429,
    "MGA": 4591.4957,
    "MKD": 56.8117,
    "MMK": 2098.8648,
    "MNT": 3449.1225,
    "MOP": 8.0045,
    "MRU": 39.9633,
    "MUR": 46.0995,
    "MVR": 15.4383,
    "MWK": 1742.4562,
    "MXN": 20.023,
    "MYR": 4.3605,
    "MZN": 63.9155,
    "NAD": 17.6999,
    "NGN": 1635.2989,
    "NIO": 36.8071,
    "NOK": 10.9933,
    "NPR": 134.5677,
    "NZD": 1.6712,
    "OMR": 0.3845,
    "PAB": 1.0,
    "PEN": 3.7686,
    "PGK": 3.964,
    "PHP": 58.2398,
    "PKR": 277.748,
    "PLN": 4.022,
    "PYG": 8035.1075,
    "QAR": 3.64,
    "RON": 4.5979,
    "RSD": 108.2311,
    "RUB": 97.1868,
    "RWF": 1368.2426,
    "SAR": 3.75,
    "SBD": 8.3177,
    "SCR": 14.5928,
    "SDG": 453.8175,
    "SEK": 10.6358,
    "SGD": 1.3224,
    "SHP": 0.7707,
    "SLE": 22.641,
    "SLL": 22641.0243,
    "SOS": 571.836,
    "SRD": 34.3578,
    "SSP": 3438.6973,
    "STN": 22.6524,
    "SYP": 12893.5079,
    "SZL": 17.6999,
    "THB": 33.7855,
    "TJS": 10.6575,
    "TMT": 3.4999,
    "TND": 3.0995,
    "TOP": 2.3384,
    "TRY": 34.3023,
    "TTD": 6.7489,
    "TVD": 1.5174,
    "TWD": 32.0482,
    "TZS": 2709.8934,
    "UAH": 41.358,
    "UGX": 3659.0554,
    "UYU": 41.609,
    "UZS": 12785.5439,
    "VES": 41.7361,
    "VND": 25370.0613,
    "VUV": 120.6132,
    "WST": 2.7512,
    "XAF": 606.489,
    "XCD": 2.7,
    "XDR": 0.7522,
    "XOF": 606.489,
    "XPF": 110.3328,
    "YER": 250.0978,
    "ZAR": 17.7002,
    "ZMW": 26.6483,
    "ZWL": 28.3676
}