{
    "USD": 1,
    "AED": 3.6725,
    "AFN": 70.7735,
    "ALL": 91.7836,
    "AMD": 388.0595,
    "ANG": 1.79,
    "AOA": 879.3391,
    "ARS": 924.75,
    "AUD": 1.4884,
    "AWG": 1.79,
    "AZN": 1.7002,
    "BAM": 1.793,
    "BBD": 2.0,
    "BDT": 117.4925,
    "BGN": 1.7926,
    "BHD": 0.376,
    "BIF": 2873.3333,
    "BMD": 1.0,
    "BND": 1.3426,
    "BOB": 6.9191,
    "BRL": 5.4969,
    "BSD": 1.0,
    "BTN": 83.6384,
    "BWP": 13.5303,
    "BYN": 3.2571,
    "BZD": 2.0,
    "CAD": 1.369,
    "CDF": 2830.3742,
    "CHF": 0.8864,
    "CLP": 923.4963,
    "CNY": 7.272,
    "COP": 3998.2975,
    "CRC": 522.6835,
    "CUP": 24.0,
    "CVE": 101.0855,
    "CZK": 23.1467,
    "DJF": 177.721,
    "DKK": 6.8414,
    "DOP": 59.0098,
    "DZD": 134.291,
    "EGP": 48.244,
    "ERN": 15.0,
    "ETB": 57.641,
    "EUR": 0.9167,
    "FJD": 2.2273,
    "FKP": 0.7715,
    "FOK": 6.8417,
    "GBP": 0.7715,
    "GEL": 2.6932,
    "GGP": 0.7715,
    "GHS": 15.5109,
    "GIP": 0.7715,
    "GMD": 66.0196,
    "GNF": 8646.4059,
    "GTQ": 7.7519,
    "GYD": 209.0514,
    "HKD": 7.8097,
    "HNL": 24.7542,
    "HRK": 6.9073,
    "HTG": 131.7717,
    "HUF": 357.8042,
    "IDR": 16158.1991,
    "ILS": 3.6464,
    "IMP": 0.7715,
    "INR": 83.6441,
    "IQD": 1309.6184,
    "IRR": 42019.5945,
    "ISK": 136.8889,
    "JEP": 0.7715,
    "JMD": 156.4609,
    "JOD": 0.709,
    "JPY": 156.9325,
    "KES": 130.1205,
    "KGS": 85.4069,
    "KHR": 4115.2329,
    "KID": 1.4884,
    "KMF": 451.0118,
    "KRW": 1383.2861,
    "KWD": 0.3055,
    "KYD": 0.8333,
    "KZT": 477.954,
    "LAK": 22012.5973,
    "LBP": 89500.0,
    "LKR": 303.4946,
    "LRD": 194.8523,
    "LSL": 18.2374,
    "LYD": 4.8292,
    "MAD": 9.8074,
    "MDL": 17.6916,
    "MGA": 4497.421,
    "MKD": 56.2812,
    "MMK": 2101.2447,
    "MNT": 3383.0024,
    "MOP": 8.044,
    "MRU": 39.7434,
    "MUR": 46.4447,
    "MVR": 15.4145,
    "MWK": 1741.1249,
    "MXN": 17.9192,
    "MYR": 4.667,
    "MZN": 63.8647,
    "NAD": 18.2374,
    "NGN": 1585.6787,
    "NIO": 36.7917,
    "NOK": 10.7859,
    "NPR": 133.8215,
    "NZD": 1.6517,
    "OMR": 0.3845,
    "PAB": 1.0,
    "PEN": 3.731,
    "PGK": 3.8809,
    "PHP": 58.3248,
    "PKR": 278.6679,
    "PLN": 3.9317,
    "PYG": 7510.9809,
    "QAR": 3.64,
    "RON": 4.5481,
    "RSD": 107.039,
    "RUB": 88.1883,
    "RWF": 1319.9339,
    "SAR": 3.75,
    "SBD": 8.459,
    "SCR": 13.7754,
    "SDG": 511.4099,
    "SEK": 10.5798,
    "SGD": 1.3425,
    "SHP": 0.7715,
    "SLE": 23.4302,
    "SLL": 23430.1954,
    "SOS": 571.3595,
    "SRD": 29.9381,
    "SSP": 1976.7883,
    "STN": 22.4604,
    "SYP": 12885.2892,
    "SZL": 18.2374,
    "THB": 36.0378,
    "TJS": 10.6643,
    "TMT": 3.498,
    "TND": 3.0984,
    "TOP": 2.3325,
    "TRY": 33.1057,
    "TTD": 6.7666,
    "TVD": 1.4884,
    "TWD": 32.651,
    "TZS": 2643.3139,
    "UAH": 41.4271,
    "UGX": 3689.55,
    "UYU": 40.1384,
    "UZS": 12555.7124,
    "VES": 36.5724,
    "VND": 25319.7518,
    "VUV": 119.4187,
    "WST": 2.728,
    "XAF": 601.349,
    "XCD": 2.7,
    "XDR": 0.7525,
    "XOF": 601.349,
    "XPF": 109.3977,
    "YER": 250.1387,
    "ZAR": 18.2323,
    "ZMW": 26.0452,
    "ZWL": 13.7241
}