{
    "USD": 1,
    "AED": 3.6725,
    "AFN": 69.506,
    "ALL": 86.0502,
    "AMD": 383.9199,
    "ANG": 1.79,
    "AOA": 918.3152,
    "ARS": 1189.67,
    "AUD": 1.5361,
    "AWG": 1.79,
    "AZN": 1.7002,
    "BAM": 1.7093,
    "BBD": 2.0,
    "BDT": 122.1734,
    "BGN": 1.7096,
    "BHD": 0.376,
    "BIF": 2976.1748,
    "BMD": 1.0,
    "BND": 1.2859,
    "BOB": 6.9199,
    "BRL": 5.6328,
    "BSD": 1.0,
    "BTN": 85.866,
    "BWP": 13.3795,
    "BYN": 3.2721,
    "BZD": 2.0,
    "CAD": 1.3665,
    "CDF": 2883.264,
    "CHF": 0.8197,
    "CLP": 937.8729,
    "CNY": 7.1785,
    "COP": 4102.9598,
    "CRC": 508.3174,
    "CUP": 24.0,
    "CVE": 96.3658,
    "CZK": 21.6865,
    "DJF": 177.721,
    "DKK": 6.5173,
    "DOP": 58.9987,
    "DZD": 131.5729,
    "EGP": 49.6666,
    "ERN": 15.0,
    "ETB": 134.3629,
    "EUR": 0.8739,
    "FJD": 2.2479,
    "FKP": 0.7366,
    "FOK": 6.5173,
    "GBP": 0.7366,
    "GEL": 2.7313,
    "GGP": 0.7366,
    "GHS": 10.6516,
    "GIP": 0.7366,
    "GMD": 72.7197,
    "GNF": 8685.5625,
    "GTQ": 7.6797,
    "GYD": 209.1932,
    "HKD": 7.8467,
    "HNL": 26.0468,
    "HRK": 6.5848,
    "HTG": 130.8666,
    "HUF": 352.4797,
    "IDR": 16267.9191,
    "ILS": 3.4908,
    "IMP": 0.7366,
    "INR": 85.8661,
    "IQD": 1309.7554,
    "IRR": 42074.0155,
    "ISK": 126.333,
    "JEP": 0.7366,
    "JMD": 159.4923,
    "JOD": 0.709,
    "JPY": 143.4502,
    "KES": 129.2023,
    "KGS": 87.5267,
    "KHR": 4017.6067,
    "KID": 1.5361,
    "KMF": 429.9541,
    "KRW": 1355.9167,
    "KWD": 0.3066,
    "KYD": 0.8333,
    "KZT": 510.0639,
    "LAK": 21644.4388,
    "LBP": 89500.0,
    "LKR": 299.2077,
    "LRD": 199.3979,
    "LSL": 17.7383,
    "LYD": 5.451,
    "MAD": 9.16,
    "MDL": 17.2614,
    "MGA": 4533.9257,
    "MKD": 54.0107,
    "MMK": 2098.5499,
    "MNT": 3570.3155,
    "MOP": 8.082,
    "MRU": 39.7449,
    "MUR": 45.5146,
    "MVR": 15.447,
    "MWK": 1742.481,
    "MXN": 19.175,
    "MYR": 4.232,
    "MZN": 63.8337,
    "NAD": 17.7383,
    "NGN": 1567.815,
    "NIO": 36.7748,
    "NOK": 10.0713,
    "NPR": 137.3857,
    "NZD": 1.6554,
    "OMR": 0.3845,
    "PAB": 1.0,
    "PEN": 3.6231,
    "PGK": 4.1568,
    "PHP": 55.6493,
    "PKR": 282.0655,
    "PLN": 3.7434,
    "PYG": 8002.1765,
    "QAR": 3.64,
    "RON": 4.421,
    "RSD": 102.5344,
    "RUB": 78.9202,
    "RWF": 1433.4968,
    "SAR": 3.75,
    "SBD": 8.5556,
    "SCR": 14.549,
    "SDG": 544.2601,
    "SEK": 9.5696,
    "SGD": 1.286,
    "SHP": 0.7366,
    "SLE": 22.7101,
    "SLL": 22710.1387,
    "SOS": 571.5442,
    "SRD": 36.7933,
    "SSP": 4612.7616,
    "STN": 21.4117,
    "SYP": 12948.0283,
    "SZL": 17.7383,
    "THB": 32.5666,
    "TJS": 10.0243,
    "TMT": 3.4998,
    "TND": 2.9449,
    "TOP": 2.3542,
    "TRY": 39.2935,
    "TTD": 6.7707,
    "TVD": 1.5361,
    "TWD": 29.8709,
    "TZS": 2659.7358,
    "UAH": 41.4643,
    "UGX": 3639.7413,
    "UYU": 41.6425,
    "UZS": 12808.0819,
    "VES": 98.5132,
    "VND": 26087.9706,
    "VUV": 120.043,
    "WST": 2.7497,
    "XAF": 573.2721,
    "XCD": 2.7,
    "XCG": 1.79,
    "XDR": 0.7334,
    "XOF": 573.2721,
    "XPF": 104.2899,
    "YER": 243.4858,
    "ZAR": 17.7372,
    "ZMW": 26.3359,
    "ZWL": 6.935
}